didauth/__init__.py
didauth/auth.py
didauth/base.py
didauth/error.py
didauth/headers.py
didauth/registry.py
didauth/utils.py
didauth/version.py
didauth/algo/__init__.py
didauth/algo/ed25519.py
didauth/algo/rsa.py
didauth/algo/secp256k1.py
didauth/ext/__init__.py
didauth/ext/aiohttp.py
didauth/ext/requests.py
didauth-1.2.3.dist-info/LICENSE
didauth-1.2.3.dist-info/METADATA
didauth-1.2.3.dist-info/WHEEL
didauth-1.2.3.dist-info/top_level.txt
didauth-1.2.3.dist-info/RECORD
